<?xml version="1.0" encoding="utf-8" ?>
<Defs>

    <!--==================== Ominous Grove Symbols Data ====================-->

    <KCSG.SymbolDef>
        <defName>SZ_CrystallineSoil</defName>
        <thing>SZ_CrystallineSoil</thing>
    </KCSG.SymbolDef>

    <KCSG.SymbolDef>
        <defName>SZ_CrystallineSand_Grove</defName>
        <thing>SZ_CrystallineSand_Grove</thing>
    </KCSG.SymbolDef>

    <KCSG.SymbolDef>
        <defName>SZ_BloodWaterShallow</defName>
        <thing>SZ_BloodWaterShallow</thing>
    </KCSG.SymbolDef>

    <KCSG.SymbolDef>
        <defName>SZ_BloodWaterChestDeep</defName>
        <thing>SZ_BloodWaterChestDeep</thing>
    </KCSG.SymbolDef>

    <KCSG.SymbolDef>
        <defName>SZ_GlisteningGrass</defName>
        <thing>SZ_GlisteningGrass</thing>
    </KCSG.SymbolDef>

    <KCSG.SymbolDef>
        <defName>SZ_GlisteningTallGrass</defName>
        <thing>SZ_GlisteningTallGrass</thing>
    </KCSG.SymbolDef>

    <KCSG.SymbolDef>
        <defName>SZ_OpulentOrchid</defName>
        <thing>SZ_OpulentOrchid</thing>
    </KCSG.SymbolDef>

    <KCSG.SymbolDef>
        <defName>SZ_BlueMoonberry</defName>
        <thing>SZ_BlueMoonberry</thing>
    </KCSG.SymbolDef>

</Defs>
